airnet/__about__.py
airnet/__init__.py
airnet/afedat.py
airnet/model.py
airnet/reader.py
airnet-1.1.0.dist-info/METADATA
airnet-1.1.0.dist-info/WHEEL
airnet-1.1.0.dist-info/entry_points.txt
airnet-1.1.0.dist-info/licenses/LICENSE.txt
airnet-1.1.0.dist-info/RECORD
